{
  "current_strategy": null,
  "current_state": null,
  "current_city": null,
  "current_locality": null,
  "current_pincode": null,
  "current_sub_brand": null,
  "states_completed": [],
  "states_fully_completed": [],
  "locality_fully_completed": [],
  "cities_completed": {},
  "cities_fully_completed": [],
  "localities_completed": {},
  "inputs_completed": [
    "DEHRADUN",
    "RAIPUR",
    "AMRITSAR",
    "NOIDA",
    "KANPUR",
    "RANCHI",
    "INDORE",
    "VARANASI",
    "ALIGARH",
    "GORAKHPUR",
    "LUCKNOW",
    "MORADABAD",
    "PATNA",
    "HALDWANI",
    "LUDHIANA",
    "UDAIPUR",
    "GHAZIABAD",
    "SILIGURI",
    "BAREILLY",
    "SAHARANPUR",
    "RAJKOT",
    "MEERUT",
    "JALANDHAR",
    "AHMEDABAD",
    "JABALPUR",
    "BILASPUR",
    "AURANGABAD",
    "SURAT",
    "CHENNAI",
    "AGARTALA",
    "GURUGRAM",
    "BHILWARA",
    "BHOPAL",
    "ALWAR",
    "AJMER",
    "BATHINDA",
    "JAIPUR",
    "AGRA",
    "PUNE",
    "HYDERABAD",
    "BANGALORE",
    "FARIDABAD",
    "ROHTAK",
    "JODHPUR",
    "MUMBAI",
    "MADURAI",
    "PATIALA",
    "GWALIOR",
    "SIKAR",
    "GAYA",
    "DHANBAD",
    "TIRUPATI",
    "CHHINDWARA",
    "PANIPAT",
    "BIKANER",
    "SATNA",
    "PATHANKOT",
    "RAIGARH",
    "ALLAHABAD",
    "KOLKATA",
    "THANE",
    "KARNAL",
    "SUKHRALI",
    "HASSAN",
    "RATLAM",
    "ANANTAPUR",
    "SONIPAT",
    "ROORKEE",
    "JAMSHEDPUR",
    "BHAVNAGAR",
    "JORHAT",
    "ANAND",
    "DURG",
    "KURUKSHETRA",
    "NANDYAL",
    "HOSHIARPUR",
    "HISAR",
    "DEORIA",
    "JHANSI",
    "SHAHJAHANPUR",
    "LATUR",
    "WEST DELHI",
    "VIJAYAWADA",
    "BHARATPUR",
    "GANDHIDHAM",
    "FAIZABAD",
    "JUNAGADH",
    "SIRSA",
    "ZIRAKPUR",
    "TINSUKIA",
    "BHIWANI",
    "AMBIKAPUR",
    "BHIWANDI",
    "DELHI CENTRAL",
    "JAMMU",
    "GHAZIPUR",
    "VADODARA",
    "DEOGHAR",
    "MOGA",
    "KARIMNAGAR",
    "AHMEDABAD CANTONM",
    "CUTTACK",
    "KOTA",
    "YAMUNANAGAR",
    "NEW DELHI",
    "AMBALA",
    "PALWAL",
    "KAITHAL",
    "MORBI",
    "KALYAN DOMBIVLI",
    "ANANTNAG",
    "SRIKAKULAM",
    "UNNAO",
    "MOTIHARI",
    "HARDOI",
    "JIND",
    "BULANDSHAHR",
    "GUWAHATI",
    "MIRZAPUR",
    "AKOLA",
    "KAMRUP",
    "CHANDIGARH",
    "MARGAO",
    "CHITTOOR",
    "JALGAON",
    "SAGARI",
    "DARBHANGA",
    "DINDIGUL",
    "KANDIVALI WEST",
    "VISAKHAPATNAM",
    "VAPI",
    "RAE BARELI",
    "SAMASTIPUR",
    "WARANGAL",
    "BHUJ",
    "DIBRUGARH",
    "MANGALORE",
    "RAJAHMUNDRY",
    "RAMPUR",
    "SANGLI",
    "PUDUCHERRY",
    "KOLAR",
    "BAHRAICH",
    "DEWAS",
    "JAMNAGAR",
    "BELLARY",
    "MUZAFFARPUR",
    "KASHIPUR",
    "MAHESANA",
    "CUDDAPAH",
    "NAGPUR",
    "MATHURA",
    "SITAPUR",
    "BALLABGARH",
    "NIZAMABAD",
    "SHIMOGA",
    "HOSUR",
    "UJJAIN",
    "BOKARO",
    "THRISSUR",
    "JAUNPUR",
    "DAHISAR EAST",
    "KORBA",
    "BALLIA",
    "BETTIAH",
    "BANDA",
    "HUBLI",
    "BENGALURU",
    "MAUNATH BHANJAN",
    "KHALAPUR",
    "NORTH WEST DELHI",
    "LAMBHUA",
    "KHARAR",
    "REWA",
    "BARNALA",
    "IMPHAL",
    "FATEHPUR",
    "BEGUSARAI",
    "LAKHIMPUR",
    "SILVASSA",
    "DIMAPUR",
    "RATNAGIRI",
    "RAICHUR",
    "PALAKKAD",
    "HUZUR",
    "TIRUVANNAMALAI",
    "FARRUKHABAD",
    "SANGRUR",
    "ETAH",
    "KHARGONE",
    "BIJAPUR",
    "NAVI MUMBAI",
    "DHAR",
    "AHMEDNAGAR",
    "DHULE",
    "SIWAN",
    "HIMATNAGAR",
    "BAHADURGARH",
    "COIMBATORE",
    "PURNIA",
    "MANDYA",
    "NEEMUCH",
    "SOUTH DELHI",
    "PALI",
    "EAST DELHI",
    "KURNOOL",
    "HANAMKONDA",
    "VIRAR",
    "BIDAR",
    "KAKINADA",
    "MUSHAHARI",
    "RAJPURA",
    "NADIAD",
    "NASHIK",
    "FIROZABAD",
    "KUMBAKONAM",
    "NALASOPARA",
    "BORIVALI WEST",
    "MYSORE",
    "AMRAVATI",
    "PRATAPGARH CITY",
    "GURDASPUR",
    "KUKATPALLY",
    "GONDA",
    "GUNTUR",
    "MANDSAUR",
    "YAVATMAL",
    "BONGAIGAON",
    "GURGAON",
    "KHANNA",
    "DHARMAPURI",
    "BUDAUN",
    "MUZAFFARNAGAR",
    "NAWABGANJ",
    "VASAI",
    "BATALA",
    "KATIHAR",
    "TEZPUR",
    "CHITRADURGA",
    "PANAJI",
    "MAINPURI",
    "PHAGWARA",
    "BELGAUM",
    "BHAGALPUR",
    "JAGDALPUR",
    "ARRAH",
    "NAINITAL",
    "DALTONGANJ",
    "GUNA",
    "JHUNJHUNU",
    "CHURCHU",
    "MIRA BHAYANDER",
    "MAHOBA",
    "BHADOHI",
    "DELHI",
    "SATARA",
    "NAWANSHAHR",
    "HOWRAH",
    "SALEM",
    "SILCHAR",
    "DAUSA",
    "JALAUN",
    "ASANSOL",
    "CHANDRAPUR",
    "SEHORE"
  ],
  "links_completed": [],
  "current_page": 1,
  "last_refresh_time": 0
}